setup.py
pysocrata/__init__.py
pysocrata/pysocrata.py
pysocrata.egg-info/PKG-INFO
pysocrata.egg-info/SOURCES.txt
pysocrata.egg-info/dependency_links.txt
pysocrata.egg-info/requires.txt
pysocrata.egg-info/top_level.txt