Metadata-Version: 1.1
Name: pysocrata
Version: 0.1.0
Summary: Python module for interfacing with Socrata open data platform metadata.
Home-page: https://github.com/ResidentMario/pysocrata
Author: Aleksey Bilogur
Author-email: aleksey.bilogur@gmail.com
License: UNKNOWN
Download-URL: https://github.com/ResidentMario/pysocrata/tarball/0.1.0
Keywords: data,socrata,open data
Platform: UNKNOWN
